deemon/__init__.py
deemon/__main__.py
deemon/cli.py
deemon/assets/index.html
deemon/assets/images/deemon.png
deemon/assets/images/discord.png
deemon/assets/images/github.png
deemon/assets/images/logo-medium.png
deemon/assets/images/logo.png
deemon/assets/images/reddit.png
deemon/cmd/__init__.py
deemon/cmd/artistconfig.py
deemon/cmd/backup.py
deemon/cmd/download.py
deemon/cmd/extra.py
deemon/cmd/generate.py
deemon/cmd/monitor.py
deemon/cmd/profile.py
deemon/cmd/refresh.py
deemon/cmd/rollback.py
deemon/cmd/search.py
deemon/cmd/show.py
deemon/cmd/tests.py
deemon/cmd/upgradelib.py
deemon/core/__init__.py
deemon/core/api.py
deemon/core/common.py
deemon/core/config.py
deemon/core/db.py
deemon/core/dmi.py
deemon/core/exceptions.py
deemon/core/logger.py
deemon/core/notifier.py
deemon/utils/__init__.py
deemon/utils/dataprocessor.py
deemon/utils/dates.py
deemon/utils/performance.py
deemon/utils/startup.py
deemon/utils/ui.py
deemon/utils/validate.py
deemon-2.22.dist-info/LICENSE
deemon-2.22.dist-info/METADATA
deemon-2.22.dist-info/WHEEL
deemon-2.22.dist-info/entry_points.txt
deemon-2.22.dist-info/top_level.txt
deemon-2.22.dist-info/RECORD
