Metadata-Version: 2.1
Name: deemon
Version: 2.22
Summary: Monitor new releases by a specified list of artists and auto download using the deemix library
Home-page: https://github.com/digitalec/deemon
Author: digitalec
License: GPL3
Classifier: License :: OSI Approved :: GNU General Public License v3 (GPLv3)
Classifier: Programming Language :: Python :: 3.8
Classifier: Operating System :: OS Independent
Requires-Python: >=3.8
License-File: LICENSE
Requires-Dist: deemix~=3.6
Requires-Dist: packaging~=23.0
Requires-Dist: requests~=2.28.0
Requires-Dist: click~=8.1.0
Requires-Dist: setuptools~=66.1.0
Requires-Dist: wheel~=0.43.0
Requires-Dist: PlexAPI~=4.5.2
Requires-Dist: tqdm~=4.61.0
Requires-Dist: mutagen~=1.46
Requires-Dist: Unidecode~=1.3.6
